worldcup_api/__init__.py
worldcup_api/api.py
worldcup_api/exceptions.py
worldcup_api/types.py
worldcup_api-1.0.0.dist-info/LICENSE
worldcup_api-1.0.0.dist-info/METADATA
worldcup_api-1.0.0.dist-info/WHEEL
worldcup_api-1.0.0.dist-info/top_level.txt
worldcup_api-1.0.0.dist-info/RECORD
